{"name":"25","stars":0,"row":1,"column":23,"star1":1,"star2":2,"star3":3,"turnCount":10,"canMoveUp":true,"balls":1}{"name":"Obstacle_Circle(Clone)","type":"Obstacle","position":{"x":-5.039999961853027,"y":2.299999237060547,"z":0.0},"rotation":{"x":0.0,"y":0.0,"z":0.0,"w":1.0},"offset":{"x":0.0,"y":0.0},"size":{"x":1.7000000476837159,"y":1.7000000476837159},"row":0,"column":0,"hp":18,"geometry":"circle"}{"name":"Obstacle_Circle(Clone)","type":"Obstacle","position":{"x":5.359999656677246,"y":1.0,"z":0.0},"rotation":{"x":0.0,"y":0.0,"z":0.0,"w":1.0},"offset":{"x":0.0,"y":0.0},"size":{"x":1.7000000476837159,"y":1.7000000476837159},"row":0,"column":1,"hp":18,"geometry":"circle"}{"name":"Obstacle_Circle(Clone)","type":"Obstacle","position":{"x":1.4599995613098145,"y":-1.6000003814697266,"z":0.0},"rotation":{"x":0.0,"y":0.0,"z":0.0,"w":1.0},"offset":{"x":0.0,"y":0.0},"size":{"x":1.7000000476837159,"y":1.7000000476837159},"row":0,"column":2,"hp":18,"geometry":"circle"}{"name":"Obstacle_Circle(Clone)","type":"Obstacle","position":{"x":-2.440000295639038,"y":-5.5,"z":0.0},"rotation":{"x":0.0,"y":0.0,"z":0.0,"w":1.0},"offset":{"x":0.0,"y":0.0},"size":{"x":1.7000000476837159,"y":1.7000000476837159},"row":0,"column":3,"hp":18,"geometry":"circle"}{"name":"Obstacle_Circle(Clone)","type":"Obstacle","position":{"x":5.359999656677246,"y":-9.399999618530274,"z":0.0},"rotation":{"x":0.0,"y":0.0,"z":0.0,"w":1.0},"offset":{"x":0.0,"y":0.0},"size":{"x":1.7000000476837159,"y":1.7000000476837159},"row":0,"column":4,"hp":18,"geometry":"circle"}{"name":"Obstacle_Circle(Clone)","type":"Obstacle","position":{"x":5.359999656677246,"y":-5.5,"z":0.0},"rotation":{"x":0.0,"y":0.0,"z":0.0,"w":1.0},"offset":{"x":0.0,"y":0.0},"size":{"x":1.7000000476837159,"y":1.7000000476837159},"row":0,"column":5,"hp":18,"geometry":"circle"}{"name":"Obstacle_Circle(Clone)","type":"Obstacle","position":{"x":-5.039999961853027,"y":-10.699999809265137,"z":0.0},"rotation":{"x":0.0,"y":0.0,"z":0.0,"w":1.0},"offset":{"x":0.0,"y":0.0},"size":{"x":1.7000000476837159,"y":1.7000000476837159},"row":0,"column":6,"hp":18,"geometry":"circle"}{"name":"Obstacle_Circle(Clone)","type":"Obstacle","position":{"x":-5.039999961853027,"y":-2.90000057220459,"z":0.0},"rotation":{"x":0.0,"y":0.0,"z":0.0,"w":1.0},"offset":{"x":0.0,"y":0.0},"size":{"x":1.7000000476837159,"y":1.7000000476837159},"row":0,"column":7,"hp":18,"geometry":"circle"}{"name":"Add_Ball(Clone)","type":"AddItem","position":{"x":-3.7400002479553224,"y":2.299999237060547,"z":0.0},"rotation":{"x":-0.7071068286895752,"y":0.0,"z":0.0,"w":0.7071068286895752},"offset":{"x":0.0,"y":0.0},"size":{"x":1.0,"y":1.0},"row":0,"column":8}{"name":"Add_Ball(Clone)","type":"AddItem","position":{"x":4.059999465942383,"y":1.0,"z":0.0},"rotation":{"x":-0.7071068286895752,"y":0.0,"z":0.0,"w":0.7071068286895752},"offset":{"x":0.0,"y":0.0},"size":{"x":1.0,"y":1.0},"row":0,"column":9}{"name":"Add_Ball(Clone)","type":"AddItem","position":{"x":0.15999984741210938,"y":-1.6000003814697266,"z":0.0},"rotation":{"x":-0.7071068286895752,"y":0.0,"z":0.0,"w":0.7071068286895752},"offset":{"x":0.0,"y":0.0},"size":{"x":1.0,"y":1.0},"row":0,"column":10}{"name":"Add_Ball(Clone)","type":"AddItem","position":{"x":-5.039999961853027,"y":-4.200000286102295,"z":0.0},"rotation":{"x":-0.7071068286895752,"y":0.0,"z":0.0,"w":0.7071068286895752},"offset":{"x":0.0,"y":0.0},"size":{"x":1.0,"y":1.0},"row":0,"column":11}{"name":"Add_Ball(Clone)","type":"AddItem","position":{"x":-1.140000343322754,"y":-5.5,"z":0.0},"rotation":{"x":-0.7071068286895752,"y":0.0,"z":0.0,"w":0.7071068286895752},"offset":{"x":0.0,"y":0.0},"size":{"x":1.0,"y":1.0},"row":0,"column":12}{"name":"Add_Ball(Clone)","type":"AddItem","position":{"x":-3.7400002479553224,"y":-10.699999809265137,"z":0.0},"rotation":{"x":-0.7071068286895752,"y":0.0,"z":0.0,"w":0.7071068286895752},"offset":{"x":0.0,"y":0.0},"size":{"x":1.0,"y":1.0},"row":0,"column":13}{"name":"Add_Ball(Clone)","type":"AddItem","position":{"x":4.059999465942383,"y":-9.399999618530274,"z":0.0},"rotation":{"x":-0.7071068286895752,"y":0.0,"z":0.0,"w":0.7071068286895752},"offset":{"x":0.0,"y":0.0},"size":{"x":1.0,"y":1.0},"row":0,"column":14}{"name":"Dead_Circle(Clone)","type":"DeadItem","position":{"x":-6.320000171661377,"y":1.0299997329711915,"z":0.0},"rotation":{"x":0.0,"y":0.0,"z":0.0,"w":1.0},"offset":{"x":0.0,"y":0.0},"size":{"x":1.7000000476837159,"y":1.7000000476837159},"row":0,"column":15,"geometry":"circle"}{"name":"Dead_Circle(Clone) (1)","type":"DeadItem","position":{"x":5.329999923706055,"y":2.489999771118164,"z":0.0},"rotation":{"x":0.0,"y":0.0,"z":0.0,"w":1.0},"offset":{"x":0.0,"y":0.0},"size":{"x":1.7000000476837159,"y":1.7000000476837159},"row":0,"column":16,"geometry":"circle"}{"name":"Dead_Circle(Clone) (2)","type":"DeadItem","position":{"x":2.7799997329711916,"y":-0.2700004577636719,"z":0.0},"rotation":{"x":0.0,"y":0.0,"z":0.0,"w":1.0},"offset":{"x":0.0,"y":0.0},"size":{"x":1.7000000476837159,"y":1.7000000476837159},"row":0,"column":17,"geometry":"circle"}{"name":"Dead_Circle(Clone) (3)","type":"DeadItem","position":{"x":-3.930000066757202,"y":-5.590000152587891,"z":0.0},"rotation":{"x":0.0,"y":0.0,"z":0.0,"w":1.0},"offset":{"x":0.0,"y":0.0},"size":{"x":1.7000000476837159,"y":1.7000000476837159},"row":0,"column":18,"geometry":"circle"}{"name":"Dead_Circle(Clone) (4)","type":"DeadItem","position":{"x":-3.870000123977661,"y":-1.6700000762939454,"z":0.0},"rotation":{"x":0.0,"y":0.0,"z":0.0,"w":1.0},"offset":{"x":0.0,"y":0.0},"size":{"x":1.7000000476837159,"y":1.7000000476837159},"row":0,"column":19,"geometry":"circle"}{"name":"Dead_Circle(Clone) (5)","type":"DeadItem","position":{"x":4.199999809265137,"y":-4.340000152587891,"z":0.0},"rotation":{"x":0.0,"y":0.0,"z":0.0,"w":1.0},"offset":{"x":0.0,"y":0.0},"size":{"x":1.7000000476837159,"y":1.7000000476837159},"row":0,"column":20,"geometry":"circle"}{"name":"Dead_Circle(Clone) (6)","type":"DeadItem","position":{"x":-6.090000152587891,"y":-9.420000076293946,"z":0.0},"rotation":{"x":0.0,"y":0.0,"z":0.0,"w":1.0},"offset":{"x":0.0,"y":0.0},"size":{"x":1.7000000476837159,"y":1.7000000476837159},"row":0,"column":21,"geometry":"circle"}{"name":"Dead_Circle(Clone) (7)","type":"DeadItem","position":{"x":6.300000190734863,"y":-8.199999809265137,"z":0.0},"rotation":{"x":0.0,"y":0.0,"z":0.0,"w":1.0},"offset":{"x":0.0,"y":0.0},"size":{"x":1.7000000476837159,"y":1.7000000476837159},"row":0,"column":22,"geometry":"circle"}{"name":"Obstacle_Circle(Clone)","type":"Obstacle","position":{"x":-5.039999961853027,"y":2.299999237060547,"z":0.0},"rotation":{"x":0.0,"y":0.0,"z":0.0,"w":1.0},"offset":{"x":0.0,"y":0.0},"size":{"x":1.7000000476837159,"y":1.7000000476837159},"row":0,"column":0,"hp":18,"geometry":"circle"}{"name":"Obstacle_Circle(Clone)","type":"Obstacle","position":{"x":5.359999656677246,"y":1.0,"z":0.0},"rotation":{"x":0.0,"y":0.0,"z":0.0,"w":1.0},"offset":{"x":0.0,"y":0.0},"size":{"x":1.7000000476837159,"y":1.7000000476837159},"row":0,"column":1,"hp":18,"geometry":"circle"}{"name":"Obstacle_Circle(Clone)","type":"Obstacle","position":{"x":1.4599995613098145,"y":-1.6000003814697266,"z":0.0},"rotation":{"x":0.0,"y":0.0,"z":0.0,"w":1.0},"offset":{"x":0.0,"y":0.0},"size":{"x":1.7000000476837159,"y":1.7000000476837159},"row":0,"column":2,"hp":18,"geometry":"circle"}{"name":"Obstacle_Circle(Clone)","type":"Obstacle","position":{"x":-2.440000295639038,"y":-5.5,"z":0.0},"rotation":{"x":0.0,"y":0.0,"z":0.0,"w":1.0},"offset":{"x":0.0,"y":0.0},"size":{"x":1.7000000476837159,"y":1.7000000476837159},"row":0,"column":3,"hp":18,"geometry":"circle"}{"name":"Obstacle_Circle(Clone)","type":"Obstacle","position":{"x":5.359999656677246,"y":-9.399999618530274,"z":0.0},"rotation":{"x":0.0,"y":0.0,"z":0.0,"w":1.0},"offset":{"x":0.0,"y":0.0},"size":{"x":1.7000000476837159,"y":1.7000000476837159},"row":0,"column":4,"hp":18,"geometry":"circle"}{"name":"Obstacle_Circle(Clone)","type":"Obstacle","position":{"x":5.359999656677246,"y":-5.5,"z":0.0},"rotation":{"x":0.0,"y":0.0,"z":0.0,"w":1.0},"offset":{"x":0.0,"y":0.0},"size":{"x":1.7000000476837159,"y":1.7000000476837159},"row":0,"column":5,"hp":18,"geometry":"circle"}{"name":"Obstacle_Circle(Clone)","type":"Obstacle","position":{"x":-5.039999961853027,"y":-10.699999809265137,"z":0.0},"rotation":{"x":0.0,"y":0.0,"z":0.0,"w":1.0},"offset":{"x":0.0,"y":0.0},"size":{"x":1.7000000476837159,"y":1.7000000476837159},"row":0,"column":6,"hp":18,"geometry":"circle"}{"name":"Obstacle_Circle(Clone)","type":"Obstacle","position":{"x":-5.039999961853027,"y":-2.90000057220459,"z":0.0},"rotation":{"x":0.0,"y":0.0,"z":0.0,"w":1.0},"offset":{"x":0.0,"y":0.0},"size":{"x":1.7000000476837159,"y":1.7000000476837159},"row":0,"column":7,"hp":18,"geometry":"circle"}{"name":"Add_Ball(Clone)","type":"AddItem","position":{"x":-3.7400002479553224,"y":2.299999237060547,"z":0.0},"rotation":{"x":-0.7071068286895752,"y":0.0,"z":0.0,"w":0.7071068286895752},"offset":{"x":0.0,"y":0.0},"size":{"x":1.0,"y":1.0},"row":0,"column":8}{"name":"Add_Ball(Clone)","type":"AddItem","position":{"x":4.059999465942383,"y":1.0,"z":0.0},"rotation":{"x":-0.7071068286895752,"y":0.0,"z":0.0,"w":0.7071068286895752},"offset":{"x":0.0,"y":0.0},"size":{"x":1.0,"y":1.0},"row":0,"column":9}{"name":"Add_Ball(Clone)","type":"AddItem","position":{"x":0.15999984741210938,"y":-1.6000003814697266,"z":0.0},"rotation":{"x":-0.7071068286895752,"y":0.0,"z":0.0,"w":0.7071068286895752},"offset":{"x":0.0,"y":0.0},"size":{"x":1.0,"y":1.0},"row":0,"column":10}{"name":"Add_Ball(Clone)","type":"AddItem","position":{"x":-5.039999961853027,"y":-4.200000286102295,"z":0.0},"rotation":{"x":-0.7071068286895752,"y":0.0,"z":0.0,"w":0.7071068286895752},"offset":{"x":0.0,"y":0.0},"size":{"x":1.0,"y":1.0},"row":0,"column":11}{"name":"Add_Ball(Clone)","type":"AddItem","position":{"x":-1.140000343322754,"y":-5.5,"z":0.0},"rotation":{"x":-0.7071068286895752,"y":0.0,"z":0.0,"w":0.7071068286895752},"offset":{"x":0.0,"y":0.0},"size":{"x":1.0,"y":1.0},"row":0,"column":12}{"name":"Add_Ball(Clone)","type":"AddItem","position":{"x":-3.7400002479553224,"y":-10.699999809265137,"z":0.0},"rotation":{"x":-0.7071068286895752,"y":0.0,"z":0.0,"w":0.7071068286895752},"offset":{"x":0.0,"y":0.0},"size":{"x":1.0,"y":1.0},"row":0,"column":13}{"name":"Add_Ball(Clone)","type":"AddItem","position":{"x":4.059999465942383,"y":-9.399999618530274,"z":0.0},"rotation":{"x":-0.7071068286895752,"y":0.0,"z":0.0,"w":0.7071068286895752},"offset":{"x":0.0,"y":0.0},"size":{"x":1.0,"y":1.0},"row":0,"column":14}{"name":"Dead_Circle(Clone)","type":"DeadItem","position":{"x":-6.320000171661377,"y":1.0299997329711915,"z":0.0},"rotation":{"x":0.0,"y":0.0,"z":0.0,"w":1.0},"offset":{"x":0.0,"y":0.0},"size":{"x":1.7000000476837159,"y":1.7000000476837159},"row":0,"column":15,"geometry":"circle"}{"name":"Dead_Circle(Clone) (1)","type":"DeadItem","position":{"x":5.329999923706055,"y":2.489999771118164,"z":0.0},"rotation":{"x":0.0,"y":0.0,"z":0.0,"w":1.0},"offset":{"x":0.0,"y":0.0},"size":{"x":1.7000000476837159,"y":1.7000000476837159},"row":0,"column":16,"geometry":"circle"}{"name":"Dead_Circle(Clone) (2)","type":"DeadItem","position":{"x":2.7799997329711916,"y":-0.2700004577636719,"z":0.0},"rotation":{"x":0.0,"y":0.0,"z":0.0,"w":1.0},"offset":{"x":0.0,"y":0.0},"size":{"x":1.7000000476837159,"y":1.7000000476837159},"row":0,"column":17,"geometry":"circle"}{"name":"Dead_Circle(Clone) (3)","type":"DeadItem","position":{"x":-3.930000066757202,"y":-5.590000152587891,"z":0.0},"rotation":{"x":0.0,"y":0.0,"z":0.0,"w":1.0},"offset":{"x":0.0,"y":0.0},"size":{"x":1.7000000476837159,"y":1.7000000476837159},"row":0,"column":18,"geometry":"circle"}{"name":"Dead_Circle(Clone) (4)","type":"DeadItem","position":{"x":-3.870000123977661,"y":-1.6700000762939454,"z":0.0},"rotation":{"x":0.0,"y":0.0,"z":0.0,"w":1.0},"offset":{"x":0.0,"y":0.0},"size":{"x":1.7000000476837159,"y":1.7000000476837159},"row":0,"column":19,"geometry":"circle"}{"name":"Dead_Circle(Clone) (5)","type":"DeadItem","position":{"x":4.199999809265137,"y":-4.340000152587891,"z":0.0},"rotation":{"x":0.0,"y":0.0,"z":0.0,"w":1.0},"offset":{"x":0.0,"y":0.0},"size":{"x":1.7000000476837159,"y":1.7000000476837159},"row":0,"column":20,"geometry":"circle"}{"name":"Dead_Circle(Clone) (6)","type":"DeadItem","position":{"x":-6.090000152587891,"y":-9.420000076293946,"z":0.0},"rotation":{"x":0.0,"y":0.0,"z":0.0,"w":1.0},"offset":{"x":0.0,"y":0.0},"size":{"x":1.7000000476837159,"y":1.7000000476837159},"row":0,"column":21,"geometry":"circle"}{"name":"Dead_Circle(Clone) (7)","type":"DeadItem","position":{"x":6.300000190734863,"y":-8.199999809265137,"z":0.0},"rotation":{"x":0.0,"y":0.0,"z":0.0,"w":1.0},"offset":{"x":0.0,"y":0.0},"size":{"x":1.7000000476837159,"y":1.7000000476837159},"row":0,"column":22,"geometry":"circle"}{"name":"Obstacle_Circle(Clone)","type":"Obstacle","position":{"x":-5.039999961853027,"y":2.299999237060547,"z":0.0},"rotation":{"x":0.0,"y":0.0,"z":0.0,"w":1.0},"offset":{"x":0.0,"y":0.0},"size":{"x":1.7000000476837159,"y":1.7000000476837159},"row":0,"column":0,"hp":18,"geometry":"circle"}{"name":"Obstacle_Circle(Clone)","type":"Obstacle","position":{"x":5.359999656677246,"y":1.0,"z":0.0},"rotation":{"x":0.0,"y":0.0,"z":0.0,"w":1.0},"offset":{"x":0.0,"y":0.0},"size":{"x":1.7000000476837159,"y":1.7000000476837159},"row":0,"column":1,"hp":18,"geometry":"circle"}{"name":"Obstacle_Circle(Clone)","type":"Obstacle","position":{"x":1.4599995613098145,"y":-1.6000003814697266,"z":0.0},"rotation":{"x":0.0,"y":0.0,"z":0.0,"w":1.0},"offset":{"x":0.0,"y":0.0},"size":{"x":1.7000000476837159,"y":1.7000000476837159},"row":0,"column":2,"hp":18,"geometry":"circle"}{"name":"Obstacle_Circle(Clone)","type":"Obstacle","position":{"x":-2.440000295639038,"y":-5.5,"z":0.0},"rotation":{"x":0.0,"y":0.0,"z":0.0,"w":1.0},"offset":{"x":0.0,"y":0.0},"size":{"x":1.7000000476837159,"y":1.7000000476837159},"row":0,"column":3,"hp":18,"geometry":"circle"}{"name":"Obstacle_Circle(Clone)","type":"Obstacle","position":{"x":5.359999656677246,"y":-9.399999618530274,"z":0.0},"rotation":{"x":0.0,"y":0.0,"z":0.0,"w":1.0},"offset":{"x":0.0,"y":0.0},"size":{"x":1.7000000476837159,"y":1.7000000476837159},"row":0,"column":4,"hp":18,"geometry":"circle"}{"name":"Obstacle_Circle(Clone)","type":"Obstacle","position":{"x":5.359999656677246,"y":-5.5,"z":0.0},"rotation":{"x":0.0,"y":0.0,"z":0.0,"w":1.0},"offset":{"x":0.0,"y":0.0},"size":{"x":1.7000000476837159,"y":1.7000000476837159},"row":0,"column":5,"hp":18,"geometry":"circle"}{"name":"Obstacle_Circle(Clone)","type":"Obstacle","position":{"x":-5.039999961853027,"y":-10.699999809265137,"z":0.0},"rotation":{"x":0.0,"y":0.0,"z":0.0,"w":1.0},"offset":{"x":0.0,"y":0.0},"size":{"x":1.7000000476837159,"y":1.7000000476837159},"row":0,"column":6,"hp":18,"geometry":"circle"}{"name":"Obstacle_Circle(Clone)","type":"Obstacle","position":{"x":-5.039999961853027,"y":-2.90000057220459,"z":0.0},"rotation":{"x":0.0,"y":0.0,"z":0.0,"w":1.0},"offset":{"x":0.0,"y":0.0},"size":{"x":1.7000000476837159,"y":1.7000000476837159},"row":0,"column":7,"hp":18,"geometry":"circle"}{"name":"Add_Ball(Clone)","type":"AddItem","position":{"x":-3.7400002479553224,"y":2.299999237060547,"z":0.0},"rotation":{"x":-0.7071068286895752,"y":0.0,"z":0.0,"w":0.7071068286895752},"offset":{"x":0.0,"y":0.0},"size":{"x":1.0,"y":1.0},"row":0,"column":8}{"name":"Add_Ball(Clone)","type":"AddItem","position":{"x":4.059999465942383,"y":1.0,"z":0.0},"rotation":{"x":-0.7071068286895752,"y":0.0,"z":0.0,"w":0.7071068286895752},"offset":{"x":0.0,"y":0.0},"size":{"x":1.0,"y":1.0},"row":0,"column":9}{"name":"Add_Ball(Clone)","type":"AddItem","position":{"x":0.15999984741210938,"y":-1.6000003814697266,"z":0.0},"rotation":{"x":-0.7071068286895752,"y":0.0,"z":0.0,"w":0.7071068286895752},"offset":{"x":0.0,"y":0.0},"size":{"x":1.0,"y":1.0},"row":0,"column":10}{"name":"Add_Ball(Clone)","type":"AddItem","position":{"x":-5.039999961853027,"y":-4.200000286102295,"z":0.0},"rotation":{"x":-0.7071068286895752,"y":0.0,"z":0.0,"w":0.7071068286895752},"offset":{"x":0.0,"y":0.0},"size":{"x":1.0,"y":1.0},"row":0,"column":11}{"name":"Add_Ball(Clone)","type":"AddItem","position":{"x":-1.140000343322754,"y":-5.5,"z":0.0},"rotation":{"x":-0.7071068286895752,"y":0.0,"z":0.0,"w":0.7071068286895752},"offset":{"x":0.0,"y":0.0},"size":{"x":1.0,"y":1.0},"row":0,"column":12}{"name":"Add_Ball(Clone)","type":"AddItem","position":{"x":-3.7400002479553224,"y":-10.699999809265137,"z":0.0},"rotation":{"x":-0.7071068286895752,"y":0.0,"z":0.0,"w":0.7071068286895752},"offset":{"x":0.0,"y":0.0},"size":{"x":1.0,"y":1.0},"row":0,"column":13}{"name":"Add_Ball(Clone)","type":"AddItem","position":{"x":4.059999465942383,"y":-9.399999618530274,"z":0.0},"rotation":{"x":-0.7071068286895752,"y":0.0,"z":0.0,"w":0.7071068286895752},"offset":{"x":0.0,"y":0.0},"size":{"x":1.0,"y":1.0},"row":0,"column":14}{"name":"Dead_Circle(Clone)","type":"DeadItem","position":{"x":-6.320000171661377,"y":1.0299997329711915,"z":0.0},"rotation":{"x":0.0,"y":0.0,"z":0.0,"w":1.0},"offset":{"x":0.0,"y":0.0},"size":{"x":1.7000000476837159,"y":1.7000000476837159},"row":0,"column":15,"geometry":"circle"}{"name":"Dead_Circle(Clone) (1)","type":"DeadItem","position":{"x":5.329999923706055,"y":2.489999771118164,"z":0.0},"rotation":{"x":0.0,"y":0.0,"z":0.0,"w":1.0},"offset":{"x":0.0,"y":0.0},"size":{"x":1.7000000476837159,"y":1.7000000476837159},"row":0,"column":16,"geometry":"circle"}{"name":"Dead_Circle(Clone) (2)","type":"DeadItem","position":{"x":2.7799997329711916,"y":-0.2700004577636719,"z":0.0},"rotation":{"x":0.0,"y":0.0,"z":0.0,"w":1.0},"offset":{"x":0.0,"y":0.0},"size":{"x":1.7000000476837159,"y":1.7000000476837159},"row":0,"column":17,"geometry":"circle"}{"name":"Dead_Circle(Clone) (3)","type":"DeadItem","position":{"x":-3.930000066757202,"y":-5.590000152587891,"z":0.0},"rotation":{"x":0.0,"y":0.0,"z":0.0,"w":1.0},"offset":{"x":0.0,"y":0.0},"size":{"x":1.7000000476837159,"y":1.7000000476837159},"row":0,"column":18,"geometry":"circle"}{"name":"Dead_Circle(Clone) (4)","type":"DeadItem","position":{"x":-3.870000123977661,"y":-1.6700000762939454,"z":0.0},"rotation":{"x":0.0,"y":0.0,"z":0.0,"w":1.0},"offset":{"x":0.0,"y":0.0},"size":{"x":1.7000000476837159,"y":1.7000000476837159},"row":0,"column":19,"geometry":"circle"}{"name":"Dead_Circle(Clone) (5)","type":"DeadItem","position":{"x":4.199999809265137,"y":-4.340000152587891,"z":0.0},"rotation":{"x":0.0,"y":0.0,"z":0.0,"w":1.0},"offset":{"x":0.0,"y":0.0},"size":{"x":1.7000000476837159,"y":1.7000000476837159},"row":0,"column":20,"geometry":"circle"}{"name":"Dead_Circle(Clone) (6)","type":"DeadItem","position":{"x":-6.090000152587891,"y":-9.420000076293946,"z":0.0},"rotation":{"x":0.0,"y":0.0,"z":0.0,"w":1.0},"offset":{"x":0.0,"y":0.0},"size":{"x":1.7000000476837159,"y":1.7000000476837159},"row":0,"column":21,"geometry":"circle"}{"name":"Dead_Circle(Clone) (7)","type":"DeadItem","position":{"x":6.300000190734863,"y":-8.199999809265137,"z":0.0},"rotation":{"x":0.0,"y":0.0,"z":0.0,"w":1.0},"offset":{"x":0.0,"y":0.0},"size":{"x":1.7000000476837159,"y":1.7000000476837159},"row":0,"column":22,"geometry":"circle"}{"name":"Obstacle_Circle(Clone)","type":"Obstacle","position":{"x":-5.039999961853027,"y":2.299999237060547,"z":0.0},"rotation":{"x":0.0,"y":0.0,"z":0.0,"w":1.0},"offset":{"x":0.0,"y":0.0},"size":{"x":1.7000000476837159,"y":1.7000000476837159},"row":0,"column":0,"hp":18,"geometry":"circle"}{"name":"Obstacle_Circle(Clone)","type":"Obstacle","position":{"x":5.359999656677246,"y":1.0,"z":0.0},"rotation":{"x":0.0,"y":0.0,"z":0.0,"w":1.0},"offset":{"x":0.0,"y":0.0},"size":{"x":1.7000000476837159,"y":1.7000000476837159},"row":0,"column":1,"hp":18,"geometry":"circle"}{"name":"Obstacle_Circle(Clone)","type":"Obstacle","position":{"x":1.4599995613098145,"y":-1.6000003814697266,"z":0.0},"rotation":{"x":0.0,"y":0.0,"z":0.0,"w":1.0},"offset":{"x":0.0,"y":0.0},"size":{"x":1.7000000476837159,"y":1.7000000476837159},"row":0,"column":2,"hp":18,"geometry":"circle"}{"name":"Obstacle_Circle(Clone)","type":"Obstacle","position":{"x":-2.440000295639038,"y":-5.5,"z":0.0},"rotation":{"x":0.0,"y":0.0,"z":0.0,"w":1.0},"offset":{"x":0.0,"y":0.0},"size":{"x":1.7000000476837159,"y":1.7000000476837159},"row":0,"column":3,"hp":18,"geometry":"circle"}{"name":"Obstacle_Circle(Clone)","type":"Obstacle","position":{"x":5.359999656677246,"y":-9.399999618530274,"z":0.0},"rotation":{"x":0.0,"y":0.0,"z":0.0,"w":1.0},"offset":{"x":0.0,"y":0.0},"size":{"x":1.7000000476837159,"y":1.7000000476837159},"row":0,"column":4,"hp":18,"geometry":"circle"}{"name":"Obstacle_Circle(Clone)","type":"Obstacle","position":{"x":5.359999656677246,"y":-5.5,"z":0.0},"rotation":{"x":0.0,"y":0.0,"z":0.0,"w":1.0},"offset":{"x":0.0,"y":0.0},"size":{"x":1.7000000476837159,"y":1.7000000476837159},"row":0,"column":5,"hp":18,"geometry":"circle"}{"name":"Obstacle_Circle(Clone)","type":"Obstacle","position":{"x":-5.039999961853027,"y":-10.699999809265137,"z":0.0},"rotation":{"x":0.0,"y":0.0,"z":0.0,"w":1.0},"offset":{"x":0.0,"y":0.0},"size":{"x":1.7000000476837159,"y":1.7000000476837159},"row":0,"column":6,"hp":18,"geometry":"circle"}{"name":"Obstacle_Circle(Clone)","type":"Obstacle","position":{"x":-5.039999961853027,"y":-2.90000057220459,"z":0.0},"rotation":{"x":0.0,"y":0.0,"z":0.0,"w":1.0},"offset":{"x":0.0,"y":0.0},"size":{"x":1.7000000476837159,"y":1.7000000476837159},"row":0,"column":7,"hp":18,"geometry":"circle"}{"name":"Add_Ball(Clone)","type":"AddItem","position":{"x":-3.7400002479553224,"y":2.299999237060547,"z":0.0},"rotation":{"x":-0.7071068286895752,"y":0.0,"z":0.0,"w":0.7071068286895752},"offset":{"x":0.0,"y":0.0},"size":{"x":1.0,"y":1.0},"row":0,"column":8}{"name":"Add_Ball(Clone)","type":"AddItem","position":{"x":4.059999465942383,"y":1.0,"z":0.0},"rotation":{"x":-0.7071068286895752,"y":0.0,"z":0.0,"w":0.7071068286895752},"offset":{"x":0.0,"y":0.0},"size":{"x":1.0,"y":1.0},"row":0,"column":9}{"name":"Add_Ball(Clone)","type":"AddItem","position":{"x":0.15999984741210938,"y":-1.6000003814697266,"z":0.0},"rotation":{"x":-0.7071068286895752,"y":0.0,"z":0.0,"w":0.7071068286895752},"offset":{"x":0.0,"y":0.0},"size":{"x":1.0,"y":1.0},"row":0,"column":10}{"name":"Add_Ball(Clone)","type":"AddItem","position":{"x":-5.039999961853027,"y":-4.200000286102295,"z":0.0},"rotation":{"x":-0.7071068286895752,"y":0.0,"z":0.0,"w":0.7071068286895752},"offset":{"x":0.0,"y":0.0},"size":{"x":1.0,"y":1.0},"row":0,"column":11}{"name":"Add_Ball(Clone)","type":"AddItem","position":{"x":-1.140000343322754,"y":-5.5,"z":0.0},"rotation":{"x":-0.7071068286895752,"y":0.0,"z":0.0,"w":0.7071068286895752},"offset":{"x":0.0,"y":0.0},"size":{"x":1.0,"y":1.0},"row":0,"column":12}{"name":"Add_Ball(Clone)","type":"AddItem","position":{"x":-3.7400002479553224,"y":-10.699999809265137,"z":0.0},"rotation":{"x":-0.7071068286895752,"y":0.0,"z":0.0,"w":0.7071068286895752},"offset":{"x":0.0,"y":0.0},"size":{"x":1.0,"y":1.0},"row":0,"column":13}{"name":"Add_Ball(Clone)","type":"AddItem","position":{"x":4.059999465942383,"y":-9.399999618530274,"z":0.0},"rotation":{"x":-0.7071068286895752,"y":0.0,"z":0.0,"w":0.7071068286895752},"offset":{"x":0.0,"y":0.0},"size":{"x":1.0,"y":1.0},"row":0,"column":14}{"name":"Dead_Circle(Clone)","type":"DeadItem","position":{"x":-6.320000171661377,"y":1.0299997329711915,"z":0.0},"rotation":{"x":0.0,"y":0.0,"z":0.0,"w":1.0},"offset":{"x":0.0,"y":0.0},"size":{"x":1.7000000476837159,"y":1.7000000476837159},"row":0,"column":15,"geometry":"circle"}{"name":"Dead_Circle(Clone) (1)","type":"DeadItem","position":{"x":5.329999923706055,"y":2.489999771118164,"z":0.0},"rotation":{"x":0.0,"y":0.0,"z":0.0,"w":1.0},"offset":{"x":0.0,"y":0.0},"size":{"x":1.7000000476837159,"y":1.7000000476837159},"row":0,"column":16,"geometry":"circle"}{"name":"Dead_Circle(Clone) (2)","type":"DeadItem","position":{"x":2.7799997329711916,"y":-0.2700004577636719,"z":0.0},"rotation":{"x":0.0,"y":0.0,"z":0.0,"w":1.0},"offset":{"x":0.0,"y":0.0},"size":{"x":1.7000000476837159,"y":1.7000000476837159},"row":0,"column":17,"geometry":"circle"}{"name":"Dead_Circle(Clone) (3)","type":"DeadItem","position":{"x":-3.930000066757202,"y":-5.590000152587891,"z":0.0},"rotation":{"x":0.0,"y":0.0,"z":0.0,"w":1.0},"offset":{"x":0.0,"y":0.0},"size":{"x":1.7000000476837159,"y":1.7000000476837159},"row":0,"column":18,"geometry":"circle"}{"name":"Dead_Circle(Clone) (4)","type":"DeadItem","position":{"x":-3.870000123977661,"y":-1.6700000762939454,"z":0.0},"rotation":{"x":0.0,"y":0.0,"z":0.0,"w":1.0},"offset":{"x":0.0,"y":0.0},"size":{"x":1.7000000476837159,"y":1.7000000476837159},"row":0,"column":19,"geometry":"circle"}{"name":"Dead_Circle(Clone) (5)","type":"DeadItem","position":{"x":4.199999809265137,"y":-4.340000152587891,"z":0.0},"rotation":{"x":0.0,"y":0.0,"z":0.0,"w":1.0},"offset":{"x":0.0,"y":0.0},"size":{"x":1.7000000476837159,"y":1.7000000476837159},"row":0,"column":20,"geometry":"circle"}{"name":"Dead_Circle(Clone) (6)","type":"DeadItem","position":{"x":-6.090000152587891,"y":-9.420000076293946,"z":0.0},"rotation":{"x":0.0,"y":0.0,"z":0.0,"w":1.0},"offset":{"x":0.0,"y":0.0},"size":{"x":1.7000000476837159,"y":1.7000000476837159},"row":0,"column":21,"geometry":"circle"}{"name":"Dead_Circle(Clone) (7)","type":"DeadItem","position":{"x":6.300000190734863,"y":-8.199999809265137,"z":0.0},"rotation":{"x":0.0,"y":0.0,"z":0.0,"w":1.0},"offset":{"x":0.0,"y":0.0},"size":{"x":1.7000000476837159,"y":1.7000000476837159},"row":0,"column":22,"geometry":"circle"}{"name":"Obstacle_Circle(Clone)","type":"Obstacle","position":{"x":-5.039999961853027,"y":2.299999237060547,"z":0.0},"rotation":{"x":0.0,"y":0.0,"z":0.0,"w":1.0},"offset":{"x":0.0,"y":0.0},"size":{"x":1.7000000476837159,"y":1.7000000476837159},"row":0,"column":0,"hp":18,"geometry":"circle"}{"name":"Obstacle_Circle(Clone)","type":"Obstacle","position":{"x":5.359999656677246,"y":1.0,"z":0.0},"rotation":{"x":0.0,"y":0.0,"z":0.0,"w":1.0},"offset":{"x":0.0,"y":0.0},"size":{"x":1.7000000476837159,"y":1.7000000476837159},"row":0,"column":1,"hp":18,"geometry":"circle"}{"name":"Obstacle_Circle(Clone)","type":"Obstacle","position":{"x":1.4599995613098145,"y":-1.6000003814697266,"z":0.0},"rotation":{"x":0.0,"y":0.0,"z":0.0,"w":1.0},"offset":{"x":0.0,"y":0.0},"size":{"x":1.7000000476837159,"y":1.7000000476837159},"row":0,"column":2,"hp":18,"geometry":"circle"}{"name":"Obstacle_Circle(Clone)","type":"Obstacle","position":{"x":-2.440000295639038,"y":-5.5,"z":0.0},"rotation":{"x":0.0,"y":0.0,"z":0.0,"w":1.0},"offset":{"x":0.0,"y":0.0},"size":{"x":1.7000000476837159,"y":1.7000000476837159},"row":0,"column":3,"hp":18,"geometry":"circle"}{"name":"Obstacle_Circle(Clone)","type":"Obstacle","position":{"x":5.359999656677246,"y":-9.399999618530274,"z":0.0},"rotation":{"x":0.0,"y":0.0,"z":0.0,"w":1.0},"offset":{"x":0.0,"y":0.0},"size":{"x":1.7000000476837159,"y":1.7000000476837159},"row":0,"column":4,"hp":18,"geometry":"circle"}{"name":"Obstacle_Circle(Clone)","type":"Obstacle","position":{"x":5.359999656677246,"y":-5.5,"z":0.0},"rotation":{"x":0.0,"y":0.0,"z":0.0,"w":1.0},"offset":{"x":0.0,"y":0.0},"size":{"x":1.7000000476837159,"y":1.7000000476837159},"row":0,"column":5,"hp":18,"geometry":"circle"}{"name":"Obstacle_Circle(Clone)","type":"Obstacle","position":{"x":-5.039999961853027,"y":-10.699999809265137,"z":0.0},"rotation":{"x":0.0,"y":0.0,"z":0.0,"w":1.0},"offset":{"x":0.0,"y":0.0},"size":{"x":1.7000000476837159,"y":1.7000000476837159},"row":0,"column":6,"hp":18,"geometry":"circle"}{"name":"Obstacle_Circle(Clone)","type":"Obstacle","position":{"x":-5.039999961853027,"y":-2.90000057220459,"z":0.0},"rotation":{"x":0.0,"y":0.0,"z":0.0,"w":1.0},"offset":{"x":0.0,"y":0.0},"size":{"x":1.7000000476837159,"y":1.7000000476837159},"row":0,"column":7,"hp":18,"geometry":"circle"}{"name":"Add_Ball(Clone)","type":"AddItem","position":{"x":-3.7400002479553224,"y":2.299999237060547,"z":0.0},"rotation":{"x":-0.7071068286895752,"y":0.0,"z":0.0,"w":0.7071068286895752},"offset":{"x":0.0,"y":0.0},"size":{"x":1.0,"y":1.0},"row":0,"column":8}{"name":"Add_Ball(Clone)","type":"AddItem","position":{"x":4.059999465942383,"y":1.0,"z":0.0},"rotation":{"x":-0.7071068286895752,"y":0.0,"z":0.0,"w":0.7071068286895752},"offset":{"x":0.0,"y":0.0},"size":{"x":1.0,"y":1.0},"row":0,"column":9}{"name":"Add_Ball(Clone)","type":"AddItem","position":{"x":0.15999984741210938,"y":-1.6000003814697266,"z":0.0},"rotation":{"x":-0.7071068286895752,"y":0.0,"z":0.0,"w":0.7071068286895752},"offset":{"x":0.0,"y":0.0},"size":{"x":1.0,"y":1.0},"row":0,"column":10}{"name":"Add_Ball(Clone)","type":"AddItem","position":{"x":-5.039999961853027,"y":-4.200000286102295,"z":0.0},"rotation":{"x":-0.7071068286895752,"y":0.0,"z":0.0,"w":0.7071068286895752},"offset":{"x":0.0,"y":0.0},"size":{"x":1.0,"y":1.0},"row":0,"column":11}{"name":"Add_Ball(Clone)","type":"AddItem","position":{"x":-1.140000343322754,"y":-5.5,"z":0.0},"rotation":{"x":-0.7071068286895752,"y":0.0,"z":0.0,"w":0.7071068286895752},"offset":{"x":0.0,"y":0.0},"size":{"x":1.0,"y":1.0},"row":0,"column":12}{"name":"Add_Ball(Clone)","type":"AddItem","position":{"x":-3.7400002479553224,"y":-10.699999809265137,"z":0.0},"rotation":{"x":-0.7071068286895752,"y":0.0,"z":0.0,"w":0.7071068286895752},"offset":{"x":0.0,"y":0.0},"size":{"x":1.0,"y":1.0},"row":0,"column":13}{"name":"Add_Ball(Clone)","type":"AddItem","position":{"x":4.059999465942383,"y":-9.399999618530274,"z":0.0},"rotation":{"x":-0.7071068286895752,"y":0.0,"z":0.0,"w":0.7071068286895752},"offset":{"x":0.0,"y":0.0},"size":{"x":1.0,"y":1.0},"row":0,"column":14}{"name":"Dead_Circle(Clone)","type":"DeadItem","position":{"x":-6.320000171661377,"y":1.0299997329711915,"z":0.0},"rotation":{"x":0.0,"y":0.0,"z":0.0,"w":1.0},"offset":{"x":0.0,"y":0.0},"size":{"x":1.7000000476837159,"y":1.7000000476837159},"row":0,"column":15,"geometry":"circle"}{"name":"Dead_Circle(Clone) (1)","type":"DeadItem","position":{"x":5.329999923706055,"y":2.489999771118164,"z":0.0},"rotation":{"x":0.0,"y":0.0,"z":0.0,"w":1.0},"offset":{"x":0.0,"y":0.0},"size":{"x":1.7000000476837159,"y":1.7000000476837159},"row":0,"column":16,"geometry":"circle"}{"name":"Dead_Circle(Clone) (2)","type":"DeadItem","position":{"x":2.7799997329711916,"y":-0.2700004577636719,"z":0.0},"rotation":{"x":0.0,"y":0.0,"z":0.0,"w":1.0},"offset":{"x":0.0,"y":0.0},"size":{"x":1.7000000476837159,"y":1.7000000476837159},"row":0,"column":17,"geometry":"circle"}{"name":"Dead_Circle(Clone) (3)","type":"DeadItem","position":{"x":-3.930000066757202,"y":-5.590000152587891,"z":0.0},"rotation":{"x":0.0,"y":0.0,"z":0.0,"w":1.0},"offset":{"x":0.0,"y":0.0},"size":{"x":1.7000000476837159,"y":1.7000000476837159},"row":0,"column":18,"geometry":"circle"}{"name":"Dead_Circle(Clone) (4)","type":"DeadItem","position":{"x":-3.870000123977661,"y":-1.6700000762939454,"z":0.0},"rotation":{"x":0.0,"y":0.0,"z":0.0,"w":1.0},"offset":{"x":0.0,"y":0.0},"size":{"x":1.7000000476837159,"y":1.7000000476837159},"row":0,"column":19,"geometry":"circle"}{"name":"Dead_Circle(Clone) (5)","type":"DeadItem","position":{"x":4.199999809265137,"y":-4.340000152587891,"z":0.0},"rotation":{"x":0.0,"y":0.0,"z":0.0,"w":1.0},"offset":{"x":0.0,"y":0.0},"size":{"x":1.7000000476837159,"y":1.7000000476837159},"row":0,"column":20,"geometry":"circle"}{"name":"Dead_Circle(Clone) (6)","type":"DeadItem","position":{"x":-6.090000152587891,"y":-9.420000076293946,"z":0.0},"rotation":{"x":0.0,"y":0.0,"z":0.0,"w":1.0},"offset":{"x":0.0,"y":0.0},"size":{"x":1.7000000476837159,"y":1.7000000476837159},"row":0,"column":21,"geometry":"circle"}{"name":"Dead_Circle(Clone) (7)","type":"DeadItem","position":{"x":6.300000190734863,"y":-8.199999809265137,"z":0.0},"rotation":{"x":0.0,"y":0.0,"z":0.0,"w":1.0},"offset":{"x":0.0,"y":0.0},"size":{"x":1.7000000476837159,"y":1.7000000476837159},"row":0,"column":22,"geometry":"circle"}{"name":"Obstacle_Circle(Clone)","type":"Obstacle","position":{"x":-5.039999961853027,"y":2.299999237060547,"z":0.0},"rotation":{"x":0.0,"y":0.0,"z":0.0,"w":1.0},"offset":{"x":0.0,"y":0.0},"size":{"x":1.7000000476837159,"y":1.7000000476837159},"row":0,"column":0,"hp":18,"geometry":"circle"}{"name":"Obstacle_Circle(Clone)","type":"Obstacle","position":{"x":5.359999656677246,"y":1.0,"z":0.0},"rotation":{"x":0.0,"y":0.0,"z":0.0,"w":1.0},"offset":{"x":0.0,"y":0.0},"size":{"x":1.7000000476837159,"y":1.7000000476837159},"row":0,"column":1,"hp":18,"geometry":"circle"}{"name":"Obstacle_Circle(Clone)","type":"Obstacle","position":{"x":1.4599995613098145,"y":-1.6000003814697266,"z":0.0},"rotation":{"x":0.0,"y":0.0,"z":0.0,"w":1.0},"offset":{"x":0.0,"y":0.0},"size":{"x":1.7000000476837159,"y":1.7000000476837159},"row":0,"column":2,"hp":18,"geometry":"circle"}{"name":"Obstacle_Circle(Clone)","type":"Obstacle","position":{"x":-2.440000295639038,"y":-5.5,"z":0.0},"rotation":{"x":0.0,"y":0.0,"z":0.0,"w":1.0},"offset":{"x":0.0,"y":0.0},"size":{"x":1.7000000476837159,"y":1.7000000476837159},"row":0,"column":3,"hp":18,"geometry":"circle"}{"name":"Obstacle_Circle(Clone)","type":"Obstacle","position":{"x":5.359999656677246,"y":-9.399999618530274,"z":0.0},"rotation":{"x":0.0,"y":0.0,"z":0.0,"w":1.0},"offset":{"x":0.0,"y":0.0},"size":{"x":1.7000000476837159,"y":1.7000000476837159},"row":0,"column":4,"hp":18,"geometry":"circle"}{"name":"Obstacle_Circle(Clone)","type":"Obstacle","position":{"x":5.359999656677246,"y":-5.5,"z":0.0},"rotation":{"x":0.0,"y":0.0,"z":0.0,"w":1.0},"offset":{"x":0.0,"y":0.0},"size":{"x":1.7000000476837159,"y":1.7000000476837159},"row":0,"column":5,"hp":18,"geometry":"circle"}{"name":"Obstacle_Circle(Clone)","type":"Obstacle","position":{"x":-5.039999961853027,"y":-10.699999809265137,"z":0.0},"rotation":{"x":0.0,"y":0.0,"z":0.0,"w":1.0},"offset":{"x":0.0,"y":0.0},"size":{"x":1.7000000476837159,"y":1.7000000476837159},"row":0,"column":6,"hp":18,"geometry":"circle"}{"name":"Obstacle_Circle(Clone)","type":"Obstacle","position":{"x":-5.039999961853027,"y":-2.90000057220459,"z":0.0},"rotation":{"x":0.0,"y":0.0,"z":0.0,"w":1.0},"offset":{"x":0.0,"y":0.0},"size":{"x":1.7000000476837159,"y":1.7000000476837159},"row":0,"column":7,"hp":18,"geometry":"circle"}{"name":"Add_Ball(Clone)","type":"AddItem","position":{"x":-3.7400002479553224,"y":2.299999237060547,"z":0.0},"rotation":{"x":-0.7071068286895752,"y":0.0,"z":0.0,"w":0.7071068286895752},"offset":{"x":0.0,"y":0.0},"size":{"x":1.0,"y":1.0},"row":0,"column":8}{"name":"Add_Ball(Clone)","type":"AddItem","position":{"x":4.059999465942383,"y":1.0,"z":0.0},"rotation":{"x":-0.7071068286895752,"y":0.0,"z":0.0,"w":0.7071068286895752},"offset":{"x":0.0,"y":0.0},"size":{"x":1.0,"y":1.0},"row":0,"column":9}{"name":"Add_Ball(Clone)","type":"AddItem","position":{"x":0.15999984741210938,"y":-1.6000003814697266,"z":0.0},"rotation":{"x":-0.7071068286895752,"y":0.0,"z":0.0,"w":0.7071068286895752},"offset":{"x":0.0,"y":0.0},"size":{"x":1.0,"y":1.0},"row":0,"column":10}{"name":"Add_Ball(Clone)","type":"AddItem","position":{"x":-5.039999961853027,"y":-4.200000286102295,"z":0.0},"rotation":{"x":-0.7071068286895752,"y":0.0,"z":0.0,"w":0.7071068286895752},"offset":{"x":0.0,"y":0.0},"size":{"x":1.0,"y":1.0},"row":0,"column":11}{"name":"Add_Ball(Clone)","type":"AddItem","position":{"x":-1.140000343322754,"y":-5.5,"z":0.0},"rotation":{"x":-0.7071068286895752,"y":0.0,"z":0.0,"w":0.7071068286895752},"offset":{"x":0.0,"y":0.0},"size":{"x":1.0,"y":1.0},"row":0,"column":12}{"name":"Add_Ball(Clone)","type":"AddItem","position":{"x":-3.7400002479553224,"y":-10.699999809265137,"z":0.0},"rotation":{"x":-0.7071068286895752,"y":0.0,"z":0.0,"w":0.7071068286895752},"offset":{"x":0.0,"y":0.0},"size":{"x":1.0,"y":1.0},"row":0,"column":13}{"name":"Add_Ball(Clone)","type":"AddItem","position":{"x":4.059999465942383,"y":-9.399999618530274,"z":0.0},"rotation":{"x":-0.7071068286895752,"y":0.0,"z":0.0,"w":0.7071068286895752},"offset":{"x":0.0,"y":0.0},"size":{"x":1.0,"y":1.0},"row":0,"column":14}{"name":"Dead_Circle(Clone)","type":"DeadItem","position":{"x":-6.320000171661377,"y":1.0299997329711915,"z":0.0},"rotation":{"x":0.0,"y":0.0,"z":0.0,"w":1.0},"offset":{"x":0.0,"y":0.0},"size":{"x":1.7000000476837159,"y":1.7000000476837159},"row":0,"column":15,"geometry":"circle"}{"name":"Dead_Circle(Clone) (1)","type":"DeadItem","position":{"x":5.329999923706055,"y":2.489999771118164,"z":0.0},"rotation":{"x":0.0,"y":0.0,"z":0.0,"w":1.0},"offset":{"x":0.0,"y":0.0},"size":{"x":1.7000000476837159,"y":1.7000000476837159},"row":0,"column":16,"geometry":"circle"}{"name":"Dead_Circle(Clone) (2)","type":"DeadItem","position":{"x":2.7799997329711916,"y":-0.2700004577636719,"z":0.0},"rotation":{"x":0.0,"y":0.0,"z":0.0,"w":1.0},"offset":{"x":0.0,"y":0.0},"size":{"x":1.7000000476837159,"y":1.7000000476837159},"row":0,"column":17,"geometry":"circle"}{"name":"Dead_Circle(Clone) (3)","type":"DeadItem","position":{"x":-3.930000066757202,"y":-5.590000152587891,"z":0.0},"rotation":{"x":0.0,"y":0.0,"z":0.0,"w":1.0},"offset":{"x":0.0,"y":0.0},"size":{"x":1.7000000476837159,"y":1.7000000476837159},"row":0,"column":18,"geometry":"circle"}{"name":"Dead_Circle(Clone) (4)","type":"DeadItem","position":{"x":-3.870000123977661,"y":-1.6700000762939454,"z":0.0},"rotation":{"x":0.0,"y":0.0,"z":0.0,"w":1.0},"offset":{"x":0.0,"y":0.0},"size":{"x":1.7000000476837159,"y":1.7000000476837159},"row":0,"column":19,"geometry":"circle"}{"name":"Dead_Circle(Clone) (5)","type":"DeadItem","position":{"x":4.199999809265137,"y":-4.340000152587891,"z":0.0},"rotation":{"x":0.0,"y":0.0,"z":0.0,"w":1.0},"offset":{"x":0.0,"y":0.0},"size":{"x":1.7000000476837159,"y":1.7000000476837159},"row":0,"column":20,"geometry":"circle"}{"name":"Dead_Circle(Clone) (6)","type":"DeadItem","position":{"x":-6.090000152587891,"y":-9.420000076293946,"z":0.0},"rotation":{"x":0.0,"y":0.0,"z":0.0,"w":1.0},"offset":{"x":0.0,"y":0.0},"size":{"x":1.7000000476837159,"y":1.7000000476837159},"row":0,"column":21,"geometry":"circle"}{"name":"Dead_Circle(Clone) (7)","type":"DeadItem","position":{"x":6.300000190734863,"y":-8.199999809265137,"z":0.0},"rotation":{"x":0.0,"y":0.0,"z":0.0,"w":1.0},"offset":{"x":0.0,"y":0.0},"size":{"x":1.7000000476837159,"y":1.7000000476837159},"row":0,"column":22,"geometry":"circle"}{"name":"Obstacle_Circle(Clone)","type":"Obstacle","position":{"x":-5.039999961853027,"y":2.299999237060547,"z":0.0},"rotation":{"x":0.0,"y":0.0,"z":0.0,"w":1.0},"offset":{"x":0.0,"y":0.0},"size":{"x":1.7000000476837159,"y":1.7000000476837159},"row":0,"column":0,"hp":18,"geometry":"circle"}{"name":"Obstacle_Circle(Clone)","type":"Obstacle","position":{"x":5.359999656677246,"y":1.0,"z":0.0},"rotation":{"x":0.0,"y":0.0,"z":0.0,"w":1.0},"offset":{"x":0.0,"y":0.0},"size":{"x":1.7000000476837159,"y":1.7000000476837159},"row":0,"column":1,"hp":18,"geometry":"circle"}{"name":"Obstacle_Circle(Clone)","type":"Obstacle","position":{"x":1.4599995613098145,"y":-1.6000003814697266,"z":0.0},"rotation":{"x":0.0,"y":0.0,"z":0.0,"w":1.0},"offset":{"x":0.0,"y":0.0},"size":{"x":1.7000000476837159,"y":1.7000000476837159},"row":0,"column":2,"hp":18,"geometry":"circle"}{"name":"Obstacle_Circle(Clone)","type":"Obstacle","position":{"x":-2.440000295639038,"y":-5.5,"z":0.0},"rotation":{"x":0.0,"y":0.0,"z":0.0,"w":1.0},"offset":{"x":0.0,"y":0.0},"size":{"x":1.7000000476837159,"y":1.7000000476837159},"row":0,"column":3,"hp":18,"geometry":"circle"}{"name":"Obstacle_Circle(Clone)","type":"Obstacle","position":{"x":5.359999656677246,"y":-9.399999618530274,"z":0.0},"rotation":{"x":0.0,"y":0.0,"z":0.0,"w":1.0},"offset":{"x":0.0,"y":0.0},"size":{"x":1.7000000476837159,"y":1.7000000476837159},"row":0,"column":4,"hp":18,"geometry":"circle"}{"name":"Obstacle_Circle(Clone)","type":"Obstacle","position":{"x":5.359999656677246,"y":-5.5,"z":0.0},"rotation":{"x":0.0,"y":0.0,"z":0.0,"w":1.0},"offset":{"x":0.0,"y":0.0},"size":{"x":1.7000000476837159,"y":1.7000000476837159},"row":0,"column":5,"hp":18,"geometry":"circle"}{"name":"Obstacle_Circle(Clone)","type":"Obstacle","position":{"x":-5.039999961853027,"y":-10.699999809265137,"z":0.0},"rotation":{"x":0.0,"y":0.0,"z":0.0,"w":1.0},"offset":{"x":0.0,"y":0.0},"size":{"x":1.7000000476837159,"y":1.7000000476837159},"row":0,"column":6,"hp":18,"geometry":"circle"}{"name":"Obstacle_Circle(Clone)","type":"Obstacle","position":{"x":-5.039999961853027,"y":-2.90000057220459,"z":0.0},"rotation":{"x":0.0,"y":0.0,"z":0.0,"w":1.0},"offset":{"x":0.0,"y":0.0},"size":{"x":1.7000000476837159,"y":1.7000000476837159},"row":0,"column":7,"hp":18,"geometry":"circle"}{"name":"Add_Ball(Clone)","type":"AddItem","position":{"x":-3.7400002479553224,"y":2.299999237060547,"z":0.0},"rotation":{"x":-0.7071068286895752,"y":0.0,"z":0.0,"w":0.7071068286895752},"offset":{"x":0.0,"y":0.0},"size":{"x":1.0,"y":1.0},"row":0,"column":8}{"name":"Add_Ball(Clone)","type":"AddItem","position":{"x":4.059999465942383,"y":1.0,"z":0.0},"rotation":{"x":-0.7071068286895752,"y":0.0,"z":0.0,"w":0.7071068286895752},"offset":{"x":0.0,"y":0.0},"size":{"x":1.0,"y":1.0},"row":0,"column":9}{"name":"Add_Ball(Clone)","type":"AddItem","position":{"x":0.15999984741210938,"y":-1.6000003814697266,"z":0.0},"rotation":{"x":-0.7071068286895752,"y":0.0,"z":0.0,"w":0.7071068286895752},"offset":{"x":0.0,"y":0.0},"size":{"x":1.0,"y":1.0},"row":0,"column":10}{"name":"Add_Ball(Clone)","type":"AddItem","position":{"x":-5.039999961853027,"y":-4.200000286102295,"z":0.0},"rotation":{"x":-0.7071068286895752,"y":0.0,"z":0.0,"w":0.7071068286895752},"offset":{"x":0.0,"y":0.0},"size":{"x":1.0,"y":1.0},"row":0,"column":11}{"name":"Add_Ball(Clone)","type":"AddItem","position":{"x":-1.140000343322754,"y":-5.5,"z":0.0},"rotation":{"x":-0.7071068286895752,"y":0.0,"z":0.0,"w":0.7071068286895752},"offset":{"x":0.0,"y":0.0},"size":{"x":1.0,"y":1.0},"row":0,"column":12}{"name":"Add_Ball(Clone)","type":"AddItem","position":{"x":-3.7400002479553224,"y":-10.699999809265137,"z":0.0},"rotation":{"x":-0.7071068286895752,"y":0.0,"z":0.0,"w":0.7071068286895752},"offset":{"x":0.0,"y":0.0},"size":{"x":1.0,"y":1.0},"row":0,"column":13}{"name":"Add_Ball(Clone)","type":"AddItem","position":{"x":4.059999465942383,"y":-9.399999618530274,"z":0.0},"rotation":{"x":-0.7071068286895752,"y":0.0,"z":0.0,"w":0.7071068286895752},"offset":{"x":0.0,"y":0.0},"size":{"x":1.0,"y":1.0},"row":0,"column":14}{"name":"Dead_Circle(Clone)","type":"DeadItem","position":{"x":-6.320000171661377,"y":1.0299997329711915,"z":0.0},"rotation":{"x":0.0,"y":0.0,"z":0.0,"w":1.0},"offset":{"x":0.0,"y":0.0},"size":{"x":1.7000000476837159,"y":1.7000000476837159},"row":0,"column":15,"geometry":"circle"}{"name":"Dead_Circle(Clone) (1)","type":"DeadItem","position":{"x":5.329999923706055,"y":2.489999771118164,"z":0.0},"rotation":{"x":0.0,"y":0.0,"z":0.0,"w":1.0},"offset":{"x":0.0,"y":0.0},"size":{"x":1.7000000476837159,"y":1.7000000476837159},"row":0,"column":16,"geometry":"circle"}{"name":"Dead_Circle(Clone) (2)","type":"DeadItem","position":{"x":2.7799997329711916,"y":-0.2700004577636719,"z":0.0},"rotation":{"x":0.0,"y":0.0,"z":0.0,"w":1.0},"offset":{"x":0.0,"y":0.0},"size":{"x":1.7000000476837159,"y":1.7000000476837159},"row":0,"column":17,"geometry":"circle"}{"name":"Dead_Circle(Clone) (3)","type":"DeadItem","position":{"x":-3.930000066757202,"y":-5.590000152587891,"z":0.0},"rotation":{"x":0.0,"y":0.0,"z":0.0,"w":1.0},"offset":{"x":0.0,"y":0.0},"size":{"x":1.7000000476837159,"y":1.7000000476837159},"row":0,"column":18,"geometry":"circle"}{"name":"Dead_Circle(Clone) (4)","type":"DeadItem","position":{"x":-3.870000123977661,"y":-1.6700000762939454,"z":0.0},"rotation":{"x":0.0,"y":0.0,"z":0.0,"w":1.0},"offset":{"x":0.0,"y":0.0},"size":{"x":1.7000000476837159,"y":1.7000000476837159},"row":0,"column":19,"geometry":"circle"}{"name":"Dead_Circle(Clone) (5)","type":"DeadItem","position":{"x":4.199999809265137,"y":-4.340000152587891,"z":0.0},"rotation":{"x":0.0,"y":0.0,"z":0.0,"w":1.0},"offset":{"x":0.0,"y":0.0},"size":{"x":1.7000000476837159,"y":1.7000000476837159},"row":0,"column":20,"geometry":"circle"}{"name":"Dead_Circle(Clone) (6)","type":"DeadItem","position":{"x":-6.090000152587891,"y":-9.420000076293946,"z":0.0},"rotation":{"x":0.0,"y":0.0,"z":0.0,"w":1.0},"offset":{"x":0.0,"y":0.0},"size":{"x":1.7000000476837159,"y":1.7000000476837159},"row":0,"column":21,"geometry":"circle"}{"name":"Dead_Circle(Clone) (7)","type":"DeadItem","position":{"x":6.300000190734863,"y":-8.199999809265137,"z":0.0},"rotation":{"x":0.0,"y":0.0,"z":0.0,"w":1.0},"offset":{"x":0.0,"y":0.0},"size":{"x":1.7000000476837159,"y":1.7000000476837159},"row":0,"column":22,"geometry":"circle"}{"name":"Obstacle_Circle(Clone)","type":"Obstacle","position":{"x":-5.039999961853027,"y":2.299999237060547,"z":0.0},"rotation":{"x":0.0,"y":0.0,"z":0.0,"w":1.0},"offset":{"x":0.0,"y":0.0},"size":{"x":1.7000000476837159,"y":1.7000000476837159},"row":0,"column":0,"hp":18,"geometry":"circle"}{"name":"Obstacle_Circle(Clone)","type":"Obstacle","position":{"x":5.359999656677246,"y":1.0,"z":0.0},"rotation":{"x":0.0,"y":0.0,"z":0.0,"w":1.0},"offset":{"x":0.0,"y":0.0},"size":{"x":1.7000000476837159,"y":1.7000000476837159},"row":0,"column":1,"hp":18,"geometry":"circle"}{"name":"Obstacle_Circle(Clone)","type":"Obstacle","position":{"x":1.4599995613098145,"y":-1.6000003814697266,"z":0.0},"rotation":{"x":0.0,"y":0.0,"z":0.0,"w":1.0},"offset":{"x":0.0,"y":0.0},"size":{"x":1.7000000476837159,"y":1.7000000476837159},"row":0,"column":2,"hp":18,"geometry":"circle"}{"name":"Obstacle_Circle(Clone)","type":"Obstacle","position":{"x":-2.440000295639038,"y":-5.5,"z":0.0},"rotation":{"x":0.0,"y":0.0,"z":0.0,"w":1.0},"offset":{"x":0.0,"y":0.0},"size":{"x":1.7000000476837159,"y":1.7000000476837159},"row":0,"column":3,"hp":18,"geometry":"circle"}{"name":"Obstacle_Circle(Clone)","type":"Obstacle","position":{"x":5.359999656677246,"y":-9.399999618530274,"z":0.0},"rotation":{"x":0.0,"y":0.0,"z":0.0,"w":1.0},"offset":{"x":0.0,"y":0.0},"size":{"x":1.7000000476837159,"y":1.7000000476837159},"row":0,"column":4,"hp":18,"geometry":"circle"}{"name":"Obstacle_Circle(Clone)","type":"Obstacle","position":{"x":5.359999656677246,"y":-5.5,"z":0.0},"rotation":{"x":0.0,"y":0.0,"z":0.0,"w":1.0},"offset":{"x":0.0,"y":0.0},"size":{"x":1.7000000476837159,"y":1.7000000476837159},"row":0,"column":5,"hp":18,"geometry":"circle"}{"name":"Obstacle_Circle(Clone)","type":"Obstacle","position":{"x":-5.039999961853027,"y":-10.699999809265137,"z":0.0},"rotation":{"x":0.0,"y":0.0,"z":0.0,"w":1.0},"offset":{"x":0.0,"y":0.0},"size":{"x":1.7000000476837159,"y":1.7000000476837159},"row":0,"column":6,"hp":18,"geometry":"circle"}{"name":"Obstacle_Circle(Clone)","type":"Obstacle","position":{"x":-5.039999961853027,"y":-2.90000057220459,"z":0.0},"rotation":{"x":0.0,"y":0.0,"z":0.0,"w":1.0},"offset":{"x":0.0,"y":0.0},"size":{"x":1.7000000476837159,"y":1.7000000476837159},"row":0,"column":7,"hp":18,"geometry":"circle"}{"name":"Add_Ball(Clone)","type":"AddItem","position":{"x":-3.7400002479553224,"y":2.299999237060547,"z":0.0},"rotation":{"x":-0.7071068286895752,"y":0.0,"z":0.0,"w":0.7071068286895752},"offset":{"x":0.0,"y":0.0},"size":{"x":1.0,"y":1.0},"row":0,"column":8}{"name":"Add_Ball(Clone)","type":"AddItem","position":{"x":4.059999465942383,"y":1.0,"z":0.0},"rotation":{"x":-0.7071068286895752,"y":0.0,"z":0.0,"w":0.7071068286895752},"offset":{"x":0.0,"y":0.0},"size":{"x":1.0,"y":1.0},"row":0,"column":9}{"name":"Add_Ball(Clone)","type":"AddItem","position":{"x":0.15999984741210938,"y":-1.6000003814697266,"z":0.0},"rotation":{"x":-0.7071068286895752,"y":0.0,"z":0.0,"w":0.7071068286895752},"offset":{"x":0.0,"y":0.0},"size":{"x":1.0,"y":1.0},"row":0,"column":10}{"name":"Add_Ball(Clone)","type":"AddItem","position":{"x":-5.039999961853027,"y":-4.200000286102295,"z":0.0},"rotation":{"x":-0.7071068286895752,"y":0.0,"z":0.0,"w":0.7071068286895752},"offset":{"x":0.0,"y":0.0},"size":{"x":1.0,"y":1.0},"row":0,"column":11}{"name":"Add_Ball(Clone)","type":"AddItem","position":{"x":-1.140000343322754,"y":-5.5,"z":0.0},"rotation":{"x":-0.7071068286895752,"y":0.0,"z":0.0,"w":0.7071068286895752},"offset":{"x":0.0,"y":0.0},"size":{"x":1.0,"y":1.0},"row":0,"column":12}{"name":"Add_Ball(Clone)","type":"AddItem","position":{"x":-3.7400002479553224,"y":-10.699999809265137,"z":0.0},"rotation":{"x":-0.7071068286895752,"y":0.0,"z":0.0,"w":0.7071068286895752},"offset":{"x":0.0,"y":0.0},"size":{"x":1.0,"y":1.0},"row":0,"column":13}{"name":"Add_Ball(Clone)","type":"AddItem","position":{"x":4.059999465942383,"y":-9.399999618530274,"z":0.0},"rotation":{"x":-0.7071068286895752,"y":0.0,"z":0.0,"w":0.7071068286895752},"offset":{"x":0.0,"y":0.0},"size":{"x":1.0,"y":1.0},"row":0,"column":14}{"name":"Dead_Circle(Clone)","type":"DeadItem","position":{"x":-6.320000171661377,"y":1.0299997329711915,"z":0.0},"rotation":{"x":0.0,"y":0.0,"z":0.0,"w":1.0},"offset":{"x":0.0,"y":0.0},"size":{"x":1.7000000476837159,"y":1.7000000476837159},"row":0,"column":15,"geometry":"circle"}{"name":"Dead_Circle(Clone) (1)","type":"DeadItem","position":{"x":5.329999923706055,"y":2.489999771118164,"z":0.0},"rotation":{"x":0.0,"y":0.0,"z":0.0,"w":1.0},"offset":{"x":0.0,"y":0.0},"size":{"x":1.7000000476837159,"y":1.7000000476837159},"row":0,"column":16,"geometry":"circle"}{"name":"Dead_Circle(Clone) (2)","type":"DeadItem","position":{"x":2.7799997329711916,"y":-0.2700004577636719,"z":0.0},"rotation":{"x":0.0,"y":0.0,"z":0.0,"w":1.0},"offset":{"x":0.0,"y":0.0},"size":{"x":1.7000000476837159,"y":1.7000000476837159},"row":0,"column":17,"geometry":"circle"}{"name":"Dead_Circle(Clone) (3)","type":"DeadItem","position":{"x":-3.930000066757202,"y":-5.590000152587891,"z":0.0},"rotation":{"x":0.0,"y":0.0,"z":0.0,"w":1.0},"offset":{"x":0.0,"y":0.0},"size":{"x":1.7000000476837159,"y":1.7000000476837159},"row":0,"column":18,"geometry":"circle"}{"name":"Dead_Circle(Clone) (4)","type":"DeadItem","position":{"x":-3.870000123977661,"y":-1.6700000762939454,"z":0.0},"rotation":{"x":0.0,"y":0.0,"z":0.0,"w":1.0},"offset":{"x":0.0,"y":0.0},"size":{"x":1.7000000476837159,"y":1.7000000476837159},"row":0,"column":19,"geometry":"circle"}{"name":"Dead_Circle(Clone) (5)","type":"DeadItem","position":{"x":4.199999809265137,"y":-4.340000152587891,"z":0.0},"rotation":{"x":0.0,"y":0.0,"z":0.0,"w":1.0},"offset":{"x":0.0,"y":0.0},"size":{"x":1.7000000476837159,"y":1.7000000476837159},"row":0,"column":20,"geometry":"circle"}{"name":"Dead_Circle(Clone) (6)","type":"DeadItem","position":{"x":-6.090000152587891,"y":-9.420000076293946,"z":0.0},"rotation":{"x":0.0,"y":0.0,"z":0.0,"w":1.0},"offset":{"x":0.0,"y":0.0},"size":{"x":1.7000000476837159,"y":1.7000000476837159},"row":0,"column":21,"geometry":"circle"}{"name":"Dead_Circle(Clone) (7)","type":"DeadItem","position":{"x":6.300000190734863,"y":-8.199999809265137,"z":0.0},"rotation":{"x":0.0,"y":0.0,"z":0.0,"w":1.0},"offset":{"x":0.0,"y":0.0},"size":{"x":1.7000000476837159,"y":1.7000000476837159},"row":0,"column":22,"geometry":"circle"}